circular_imports/__init__.py
circular_imports/cli.py
circular_imports/find_deps.py
circular_imports/graph.py
circular_imports/graph_test.py
circular_imports-0.1.4.dist-info/METADATA
circular_imports-0.1.4.dist-info/WHEEL
circular_imports-0.1.4.dist-info/entry_points.txt
circular_imports-0.1.4.dist-info/RECORD
