Metadata-Version: 2.1
Name: circular-imports
Version: 0.1.4
Summary: Detect circular imports in codebase.
Author: Bruno Costa
Author-email: bruno@abstra.app
Requires-Python: >=3.8
Classifier: Programming Language :: Python :: 3
Classifier: Programming Language :: Python :: 3.8
Classifier: Programming Language :: Python :: 3.9
Classifier: Programming Language :: Python :: 3.10
Classifier: Programming Language :: Python :: 3.11
Classifier: Programming Language :: Python :: 3.12
Classifier: Programming Language :: Python :: 3.13
